audioic/AcousticGrandPiano.wav
audioic/audioic.py
audioic/gmm.pt
audioic-0.1.3.dist-info/METADATA
audioic-0.1.3.dist-info/WHEEL
audioic-0.1.3.dist-info/top_level.txt
audioic-0.1.3.dist-info/RECORD
