Metadata-Version: 2.4
Name: audioic
Version: 0.1.3
Summary: AudioIC Project
Author-email: Mathias Rose Bjare <muthissar@gmail.com>
License-Expression: CC-BY-NC-4.0
Project-URL: homepage, https://github.com/sonycslparis/audioic
Project-URL: issues, https://github.com/sonycslparis/audioic/issues
Requires-Python: <3.13,>=3.11
Requires-Dist: music2latent
Requires-Dist: numpy<2.0.0,>=1.23.4
Requires-Dist: soundfile>=0.12.1
Requires-Dist: torch<2.6.0,>=2.3.0
Requires-Dist: torchaudio<2.6.0,>=2.3.0
Requires-Dist: librosa>=0.10.2.post1
Requires-Dist: x-transformers==1.42
Requires-Dist: einops>=0.8.0
Requires-Dist: jsonargparse[signatures]<5.0.0,>=4.32.0
Provides-Extra: demo
Requires-Dist: ipykernel; extra == "demo"
Requires-Dist: matplotlib; extra == "demo"
